AUTHORS
INSTALL
LICENSE
MANIFEST.in
README
setup.py
doc/foo
matanui/__init__.py
matanui/config.py
matanui/exceptions.py
matanui/inout.py
matanui/mongogridfs.py
matanui/operations.py
matanui/request.py
matanui/service.py
matanui/storerinterface.py
matanui.egg-info/PKG-INFO
matanui.egg-info/SOURCES.txt
matanui.egg-info/dependency_links.txt
matanui.egg-info/top_level.txt
test/__init__.py
test/mongogridfs_test.py
test/operations_test.py
test/request_test.py
test/service_test.py
test/storerinterface_test.py
test/testdata.py