Metadata-Version: 1.1
Name: matanui
Version: 0.1.0
Summary: MataNui Replicating Grid Data Server
Home-page: https://launchpad.net/matanui/
Author: Guy K. Kloss
Author-email: guy.kloss@aut.ac.nz
License: Lesser General Public License v3
Download-URL: https://launchpad.net/matanui/+download
Keywords: dataserver mongodb rest restful json webservice gridfs grid distributed
Platform: UNKNOWN
Classifier: Development Status :: 3 - Alpha
Classifier: Intended Audience :: Science/Research
Classifier: Operating System :: OS Independent
Classifier: Programming Language :: Python :: 2
Classifier: License :: OSI Approved :: GNU Library or Lesser General Public License (LGPL)
Classifier: Environment :: Web Environment
Classifier: Topic :: Internet
Classifier: Topic :: Internet :: WWW/HTTP
Classifier: Topic :: Internet :: WWW/HTTP :: WSGI :: Application
Classifier: Topic :: System :: Distributed Computing
Classifier: Topic :: System :: Filesystems
Classifier: Topic :: System :: Archiving
Provides: matanui
